chatdb/__init__.py
chatdb/matching.py
chatdb/models.py
chatdb/util.py
chatdb/tools/__init__.py
chatdb/tools/twitter.py
chatdb-0.1.0.dist-info/LICENSE
chatdb-0.1.0.dist-info/METADATA
chatdb-0.1.0.dist-info/WHEEL
chatdb-0.1.0.dist-info/top_level.txt
chatdb-0.1.0.dist-info/RECORD
