Metadata-Version: 2.1
Name: chatdb
Version: 0.1.0
Summary: ChatDB is a toolkit to easily store chat messages in DB.
Home-page: https://github.com/A03ki/chatdb
Author: Aki
Author-email: a03ki04@gmail.com
License: MIT License
Keywords: DB Neo4j NLP
Platform: UNKNOWN
Classifier: License :: OSI Approved :: MIT License
Classifier: Programming Language :: Python :: 3.6
Classifier: Programming Language :: Python :: 3.7
Classifier: Programming Language :: Python :: 3.8
Requires-Python: >=3.6, <3.9
Requires-Dist: py2neo
